LICENSE
README.md
setup.py
BMINet/__init__.py
BMINet/plot.py
BMINet.egg-info/PKG-INFO
BMINet.egg-info/SOURCES.txt
BMINet.egg-info/dependency_links.txt
BMINet.egg-info/top_level.txt
BMINet/Interaction/__init__.py
BMINet/Interaction/feature_select.py
BMINet/Interaction/model_explanation.py
BMINet/Interaction/network_analyzation.py
BMINet/Interaction/network_construction.py
BMINet/Interaction/stacking_model.py