Metadata-Version: 2.1
Name: BMINet
Version: 0.0.1
Summary: Machine Learning and Graph based tool for detecting and analyzing Bone-Muscle Interactions
Author: Spencer Wang
Author-email: jrwangspencer@stu.suda.edu.cn
Keywords: python,Net-BMI,Interaction,Network,Bone-Muscle,windows
Classifier: Development Status :: 1 - Planning
Classifier: Intended Audience :: Developers
Classifier: Programming Language :: Python :: 3
Classifier: Operating System :: Unix
Classifier: Operating System :: MacOS :: MacOS X
Classifier: Operating System :: Microsoft :: Windows
License-File: LICENSE
